tc_hivemind_backend/__init__.py
tc_hivemind_backend/ingest_qdrant.py
tc_hivemind_backend/pg_vector_access.py
tc_hivemind_backend/qdrant_vector_access.py
tc_hivemind_backend/db/__init__.py
tc_hivemind_backend/db/credentials.py
tc_hivemind_backend/db/modules_base.py
tc_hivemind_backend/db/mongo.py
tc_hivemind_backend/db/pg_db_utils.py
tc_hivemind_backend/db/postgresql.py
tc_hivemind_backend/db/qdrant.py
tc_hivemind_backend/db/redis.py
tc_hivemind_backend/db/redis_kv_store.py
tc_hivemind_backend/db/utils/__init__.py
tc_hivemind_backend/db/utils/delete_data.py
tc_hivemind_backend/db/utils/model_hyperparams.py
tc_hivemind_backend/db/utils/preprocess_text.py
tc_hivemind_backend/embeddings/__init__.py
tc_hivemind_backend/embeddings/cohere.py
tc_hivemind_backend/tests/__init__.py
tc_hivemind_backend/tests/integration/__init__.py
tc_hivemind_backend/tests/integration/test_delete_data.py
tc_hivemind_backend/tests/integration/test_ingestion_pipeline_etl.py
tc_hivemind_backend/tests/integration/test_modules_base_query.py
tc_hivemind_backend/tests/integration/test_modules_base_query_token.py
tc_hivemind_backend/tests/integration/test_mongo_singleton.py
tc_hivemind_backend/tests/integration/test_pg_vector_access.py
tc_hivemind_backend/tests/integration/test_qdrant_vector_access.py
tc_hivemind_backend/tests/unit/__init__.py
tc_hivemind_backend/tests/unit/test_base_processor.py
tc_hivemind_backend/tests/unit/test_convert_tuple_str.py
tc_hivemind_backend/tests/unit/test_ingestion_pipeline.py
tc_hivemind_backend/tests/unit/test_load_db_credentials.py
tc_hivemind_backend/tests/unit/test_load_model_hyperparameters.py
tc_hivemind_backend/tests/unit/test_mongo_singleton.py
tc_hivemind_backend/tests/unit/test_qdrant_singleton.py
tc_hivemind_backend/tests/unit/test_redis_singleton.py
tc_hivemind_backend-1.4.8.dist-info/METADATA
tc_hivemind_backend-1.4.8.dist-info/WHEEL
tc_hivemind_backend-1.4.8.dist-info/top_level.txt
tc_hivemind_backend-1.4.8.dist-info/RECORD
