Metadata-Version: 2.4
Name: tc-hivemind-backend
Version: 1.4.8
Summary: This repository is a shared library for together hivemind etl and bot codes.
Author: Mohammad Amin Dadgar, TogetherCrew
Maintainer: Mohammad Amin Dadgar
Maintainer-email: dadgaramin96@gmail.com
Requires-Dist: numpy>=1.24.1
Requires-Dist: pytest>=7.2.0
Requires-Dist: pytest-cov>=4.0.0
Requires-Dist: coverage<8.0.0,>=7.2.5
Requires-Dist: python-dotenv>=1.0.0
Requires-Dist: tc_messageBroker>=1.6.3
Requires-Dist: pymongo<5.0.0,>=4.3.3
Requires-Dist: neo4j<6.0.0,>=5.8.0
Requires-Dist: llama-index-core==0.10.68.post1
Requires-Dist: llama-index-embeddings-openai<1.0.0,>=0.1.0
Requires-Dist: llama-index-llms-openai<1.0.0,>=0.1.0
Requires-Dist: llama-index-legacy
Requires-Dist: sqlalchemy[asyncio]
Requires-Dist: cohere<5.0.0,>=4.39
Requires-Dist: pgvector
Requires-Dist: asyncpg
Requires-Dist: psycopg2-binary
Requires-Dist: llama-index-vector-stores-qdrant==0.2.8
Requires-Dist: qdrant-client==1.12.1
Requires-Dist: llama-index-storage-docstore-redis<1.0.0,>=0.1.0
Requires-Dist: llama-index-storage-docstore-mongodb<1.0.0,>=0.1.0
Requires-Dist: spacy
Dynamic: author
Dynamic: description
Dynamic: maintainer
Dynamic: maintainer-email
Dynamic: requires-dist
Dynamic: summary
